hardlinker
