Metadata-Version: 1.0
Name: hardlinker
Version: 0.5.2
Summary: Find identical files and hardlink them
Home-page: http://github.com/ralphbean/hardlinker
Author: Ralph Bean
Author-email: ralph.bean@gmail.com
License: GPLv3+
Platform: UNKNOWN
